LICENSE
pckit/__init__.py
pckit/_mpi_check.py
pckit/_typevars.py
pckit/cache.py
pckit/comsol/__init__.py
pckit/comsol/model.py
pckit/comsol/worker.py
pckit/logging_utils.py
pckit/models.py
pckit/solvers.py
pckit/task.py
pckit/workers.py
pckit-0.5.3.dist-info/LICENSE
pckit-0.5.3.dist-info/METADATA
pckit-0.5.3.dist-info/WHEEL
pckit-0.5.3.dist-info/RECORD
