Metadata-Version: 2.1
Name: pckit
Version: 0.5.3
Summary: A simple package for parallel computing with Python
Home-page: https://github.com/djiboshin/pckit
License: MIT
Author: djiboshin
Requires-Python: >=3.9,<4.0
Classifier: License :: OSI Approved :: MIT License
Classifier: Programming Language :: Python :: 3
Classifier: Programming Language :: Python :: 3.9
Classifier: Programming Language :: Python :: 3.10
Classifier: Programming Language :: Python :: 3.11
Classifier: Programming Language :: Python :: 3.12
Requires-Dist: numpy (>=1.25.2,<2.0.0)
Project-URL: Repository, https://github.com/djiboshin/pckit
